README.md
setup.py
helios/Rk4Derivative.py
helios/Rk4Utils.py
helios/__init__.py
helios/aerodynamic_para.py
helios/density_and_temp.py
helios/import_data.py
helios/initialize.py
helios/main.py
helios/output_pdf.py
helios/predictor.py
helios/propulsion_para.py
helios/rocket_sim.py
helios/test.py
helios/turbulance_generator.py
helios/wind_forces.py
helios_sim.egg-info/PKG-INFO
helios_sim.egg-info/SOURCES.txt
helios_sim.egg-info/dependency_links.txt
helios_sim.egg-info/entry_points.txt
helios_sim.egg-info/requires.txt
helios_sim.egg-info/top_level.txt