Metadata-Version: 2.1
Name: helios-sim
Version: 0.1.0
Summary: 6 DOF Rocket Simulator
Author: Ronan
Author-email: ronanmarkdsouza@gmail.com
